pyguess-0.2.2.dist-info/METADATA
pyguess-0.2.2.dist-info/WHEEL
pyguess/__init__.py
pyguess/__init__.pyi
pyguess/py.typed
pyguess/pyguess.abi3.so
pyguess-0.2.2.dist-info/RECORD
