Metadata-Version: 2.1
Name: pyguess
Version: 0.2.2
Classifier: Programming Language :: Rust
Classifier: Programming Language :: Python :: Implementation :: CPython
Classifier: Programming Language :: Python :: Implementation :: PyPy
Summary: The Python bindings to guess-rs
Keywords: guess_rs
Home-Page: https://github.com/Novalytica/guess-rs/pyguess
Author: Vladyslav Rezohlazov <vladyslav.rezohlazov@novalytica.com>
Author-email: Vladyslav Rezohlazov <vladyslav.rezohlazov@novalytica.com>
License: MIT
Requires-Python: >=3.10
Project-URL: Source Code, https://github.com/Novalytica/guess-rs.git
